raphtory/__init__.py
raphtory/py.typed
raphtory_stubs-0.1.3.dist-info/LICENSE
raphtory_stubs-0.1.3.dist-info/METADATA
raphtory_stubs-0.1.3.dist-info/WHEEL
raphtory_stubs-0.1.3.dist-info/top_level.txt
raphtory_stubs-0.1.3.dist-info/RECORD
