Metadata-Version: 2.1
Name: raphtory-stubs
Version: 0.1.3
Summary: Type stubs for the Raphtory library
Author-email: Jett Hollister <jetthollister@pm.me>
License: MIT
Project-URL: Homepage, https://github.com/hallofstairs/raphtory-stubs
Project-URL: Bug Tracker, https://github.com/hallofstairs/raphtory-stubs/issues
Keywords: raphtory,stubs,type hints
Classifier: Programming Language :: Python :: 3
Classifier: License :: OSI Approved :: MIT License
Classifier: Operating System :: OS Independent
Classifier: Typing :: Typed
Requires-Python: >=3.7
License-File: LICENSE
Requires-Dist: raphtory
Requires-Dist: networkx
Requires-Dist: pandas
